spectrapepper/__init__.py
spectrapepper/functions.py
spectrapepper/datasets/params.txt
spectrapepper/datasets/spectras.txt
spectrapepper/datasets/targets.txt
spectrapepper-0.1.10.dist-info/LICENSE
spectrapepper-0.1.10.dist-info/METADATA
spectrapepper-0.1.10.dist-info/WHEEL
spectrapepper-0.1.10.dist-info/dependency_links.txt
spectrapepper-0.1.10.dist-info/top_level.txt
spectrapepper-0.1.10.dist-info/RECORD
