Metadata-Version: 2.1
Name: spectrapepper
Version: 0.1.10
Summary: A Python package to simplify and accelerate analysis of spectroscopy data
Home-page: https://github.com/spectrapepper/spectrapepper
Author: spectrapepper
Author-email: spectrapepper@gmail.com
License: MIT license
Keywords: spectrapepper
Classifier: Development Status :: 2 - Pre-Alpha
Classifier: Intended Audience :: Developers
Classifier: License :: OSI Approved :: MIT License
Classifier: Natural Language :: English
Classifier: Programming Language :: Python :: 3
Classifier: Programming Language :: Python :: 3.7
Classifier: Programming Language :: Python :: 3.8
Classifier: Programming Language :: Python :: 3.9
Classifier: Programming Language :: Python :: 3.10
Requires-Python: >=3.7
License-File: LICENSE
Requires-Dist: numpy >=1.21
Requires-Dist: pandas
Requires-Dist: scipy >=1.7.0
Requires-Dist: matplotlib
